pyxfr/__init__.py
pyxfr/pyxfr.cpython-313-darwin.so
pyxfr/pyxfr_utils.py
pyxfr/data/transferase_data_0.6.3.json
pyxfr-0.6.3.dist-info/METADATA
pyxfr-0.6.3.dist-info/WHEEL
pyxfr-0.6.3.dist-info/licenses/LICENSE
pyxfr-0.6.3.dist-info/RECORD
