Metadata-Version: 2.4
Name: pyxfr
Version: 0.6.3
Summary: The Transferase Python API
Project-URL: Homepage, https://github.com/andrewdavidsmith/transferase
Project-URL: Documentation, https://github.com/andrewdavidsmith/transferase
Project-URL: Repository, https://github.com/andrewdavidsmith/transferase
Project-URL: Issues, https://github.com/andrewdavidsmith/transferase/issues
Author-email: Andrew D Smith <andrewds@usc.edu>
Maintainer-email: Andrew D Smith <andrewds@usc.edu>
License: MIT
License-File: LICENSE
Keywords: DNA methylation,epigenetics,epigenomics,genomics,methylation,methylome
Classifier: Development Status :: 4 - Beta
Classifier: Intended Audience :: Developers
Classifier: Intended Audience :: Education
Classifier: Intended Audience :: Healthcare Industry
Classifier: Intended Audience :: Science/Research
Classifier: Programming Language :: Python :: 3.12
Classifier: Programming Language :: Python :: 3.13
Classifier: Programming Language :: Python :: Implementation :: CPython
Classifier: Topic :: Scientific/Engineering :: Bio-Informatics
Classifier: Topic :: Scientific/Engineering :: Information Analysis
Classifier: Topic :: Scientific/Engineering :: Medical Science Apps.
Requires-Python: >=3.12
Requires-Dist: numpy>=2.0
